airbyte_cdk_bootstrap/__init__.py
airbyte_cdk_bootstrap/auth/__init__.py
airbyte_cdk_bootstrap/auth/auth.py
airbyte_cdk_bootstrap/auth/exceptions.py
airbyte_cdk_bootstrap/auth/models.py
airbyte_cdk_bootstrap/models.py
airbyte_cdk_bootstrap/source/__init__.py
airbyte_cdk_bootstrap/source/miltithreading_source/__init__.py
airbyte_cdk_bootstrap/source/miltithreading_source/source.py
airbyte_cdk_bootstrap/source/models.py
airbyte_cdk_bootstrap/source/source.py
airbyte_cdk_bootstrap/source/spec.py
airbyte_cdk_bootstrap/streams/__init__.py
airbyte_cdk_bootstrap/streams/multithread_stream/__init__.py
airbyte_cdk_bootstrap/streams/multithread_stream/stream.py
airbyte_cdk_bootstrap/streams/stream.py
airbyte_cdk_bootstrap/utils.py
airbyte_cdk_bootstrap-0.1.0.dist-info/WHEEL
airbyte_cdk_bootstrap-0.1.0.dist-info/METADATA
airbyte_cdk_bootstrap-0.1.0.dist-info/RECORD
